LICENSE
MANIFEST.in
README.rst
setup.py
django_users_api.egg-info/PKG-INFO
django_users_api.egg-info/SOURCES.txt
django_users_api.egg-info/dependency_links.txt
django_users_api.egg-info/not-zip-safe
django_users_api.egg-info/top_level.txt
tests/__init__.py
tests/settings.py
users_api/__init__.py
users_api/authorization.py
users_api/common.py
users_api/models.py
users_api/urls.py
users_api/api/__init__.py
users_api/api/groups.py
users_api/api/permissions.py
users_api/api/users.py
users_api/tests/__init__.py
users_api/tests/groups.py
users_api/tests/permissions.py
users_api/tests/users.py