Metadata-Version: 1.1
Name: django-users-api
Version: 0.1
Summary: Django users RESTful API using Tastypie.
Home-page: https://github.com/mohabusama/django-users-api
Author: Mohab Usama
Author-email: mohab.usama@gmail.com
License: The MIT License (MIT)
